pyglassdoor/__init__.py
pyglassdoor/__main__.py
pyglassdoor/cli.py
pyglassdoor/interviews.py
pyglassdoor/reviews.py
pyglassdoor/salaries.py
pyglassdoor/session.py
pyglassdoor-0.5.0.dist-info/AUTHORS.rst
pyglassdoor-0.5.0.dist-info/LICENSE
pyglassdoor-0.5.0.dist-info/METADATA
pyglassdoor-0.5.0.dist-info/WHEEL
pyglassdoor-0.5.0.dist-info/entry_points.txt
pyglassdoor-0.5.0.dist-info/top_level.txt
pyglassdoor-0.5.0.dist-info/RECORD
